youtube_drive/__init__.py
youtube_drive/__main__.py
youtube_drive/main.py
youtube_drive/youtube_codec.py
youtube_drive-0.0.1.data/scripts/youtube-drive
youtube_drive-0.0.1.dist-info/LICENSE
youtube_drive-0.0.1.dist-info/METADATA
youtube_drive-0.0.1.dist-info/WHEEL
youtube_drive-0.0.1.dist-info/dependency_links.txt
youtube_drive-0.0.1.dist-info/entry_points.txt
youtube_drive-0.0.1.dist-info/top_level.txt
youtube_drive-0.0.1.dist-info/RECORD
