Metadata-Version: 2.1
Name: youtube-drive
Version: 0.0.1
Summary: Store files as YouTube videos
Home-page: https://github.com/lewangdev/youtube-drive
Author: Le Wang
Author-email: lewang.dev@gmail.com
License: Apache-2.0 license
Classifier: Topic :: Internet :: WWW/HTTP
Classifier: Development Status :: 4 - Beta
Classifier: Environment :: Console
Classifier: License :: OSI Approved :: Apache Software License
Classifier: Operating System :: POSIX
Classifier: Operating System :: Microsoft :: Windows
Classifier: Programming Language :: Python :: 3
License-File: LICENSE
Requires-Dist: numpy
Requires-Dist: opencv-python
Requires-Dist: youtube-dl
Requires-Dist: pillow
Requires-Dist: youtube-upload (==0.8.0)
